{"singlePage": [], "startSite": "", "filingNum": "", "onePageListNum": 15, "commentLabelColor": "#006b75", "yearColorList": ["#bc4c00", "#0969da", "#1f883d", "#A333D0"], "i18n": "CN", "themeMode": "manual", "dayTheme": "light", "nightTheme": "dark", "urlMode": "pinyin", "script": "", "style": "", "bottomText": "", "showPostSource": 1, "iconList": {}, "UTC": 8, "rssSplit": "sentence", "exlink": {}, "title": "\u5766\u514b\u8fd8\u4e0d\u524a", "subTitle": "ban\u732a\u516b\u6212\u4ece\u6211\u505a\u8d77", "avatarUrl": "https://images.asuna.onflashdrive.app/file/c7eba0ac45bbe39b6ff45.png", "GMEEK_VERSION": "last", "postListJson": {"P1": {"htmlDir": "docs/post/chao-qing-bi-zhi-fen-xiang.html", "labels": ["\u58c1\u7eb8"], "postTitle": "\u8d85\u6e05\u58c1\u7eb8\u5206\u4eab", "postUrl": "post/chao-qing-bi-zhi-fen-xiang.html", "postSourceUrl": "https://github.com/shadowgarden1314/issueblog/issues/1", "commentNum": 0, "wordCount": 263, "description": "\u4f0a\u857e\u5a1c\r\n![](https://images.asuna.onflashdrive.app/file/05fd077ea646d09e89425.jpg)\r\n![](https://img.krito.onflashdrive.app/2024/04/4519165ddbe487cb5296e3f3197d5c5f.jpg)\r\n![](https://cdn.jsdelivr.net/gh/shadowgarden1314/imagegeren/26DFFA4DD69200C19F1E1DB1BAC535A1.jpg)\u3002", "top": 0, "createdAt": 1713917790, "style": "", "script": "", "createdDate": "2024-04-24", "dateLabelColor": "#bc4c00"}, "P2": {"htmlDir": "docs/post/bi-zhi-fen-xiang.html", "labels": ["\u58c1\u7eb8"], "postTitle": "\u58c1\u7eb8\u5206\u4eab", "postUrl": "post/bi-zhi-fen-xiang.html", "postSourceUrl": "https://github.com/shadowgarden1314/issueblog/issues/2", "commentNum": 0, "wordCount": 147, "description": "\u4f0a\u857e\u5a1c\r\n\r\n\r\n![26DFFA4DD69200C19F1E1DB1BAC535A1](https://github.com/shadowgarden1314/issueblog/assets/131418013/793e1bf6-8415-4210-b50e-5ecb857db96d)\r\n\u3002", "top": 0, "createdAt": 1713918000, "style": "", "script": "", "createdDate": "2024-04-24", "dateLabelColor": "#bc4c00"}, "P3": {"htmlDir": "docs/post/bi-zhi-fen-xiang-6.html", "labels": ["\u58c1\u7eb8"], "postTitle": "\u58c1\u7eb8\u5206\u4eab6", "postUrl": "post/bi-zhi-fen-xiang-6.html", "postSourceUrl": "https://github.com/shadowgarden1314/issueblog/issues/3", "commentNum": 0, "wordCount": 79, "description": "\u9ec4\u6cc9\r\n![](https://images.asuna.onflashdrive.app/file/6cecd5783a849e14e3a36.jpg)\r\n\u3002", "top": 0, "createdAt": 1713970120, "style": "", "script": "", "createdDate": "2024-04-24", "dateLabelColor": "#bc4c00"}}, "singeListJson": {}, "labelColorDict": {"bug": "#d73a4a", "documentation": "#0075ca", "duplicate": "#cfd3d7", "enhancement": "#a2eeef", "good first issue": "#7057ff", "help wanted": "#008672", "invalid": "#e4e669", "question": "#d876e3", "wontfix": "#ffffff", "\u58c1\u7eb8": "#bfdadc"}, "displayTitle": "\u5766\u514b\u8fd8\u4e0d\u524a", "faviconUrl": "https://images.asuna.onflashdrive.app/file/c7eba0ac45bbe39b6ff45.png", "homeUrl": "https://shadowgarden1314.github.io/issueblog", "prevUrl": "disabled", "nextUrl": "disabled"}